Metadata-Version: 2.1
Name: discord-py-dashboard
Version: 0.3.1
Summary: Веб-перехватчик и расширение discord.py на основе запросов для создания панели управления ботом.
Home-page: https://github.com/MaseZev/discord-py-dashboard
Author: MaseZev
License: mit
Platform: UNKNOWN
Classifier: Natural Language :: English
Classifier: Operating System :: OS Independent
Classifier: Programming Language :: Python :: 3.5
Classifier: Programming Language :: Python :: 3.6
Classifier: Programming Language :: Python :: 3.7
Classifier: Programming Language :: Python :: 3.8
Classifier: Topic :: Internet
Classifier: Topic :: Software Development :: Libraries
Classifier: Topic :: Software Development :: Libraries :: Python Modules
Classifier: Topic :: Utilities
Requires-Python: >=3.5.3
